photobooth/__init__.py
photobooth/cli.py
photobooth/config.py
photobooth/adapters/__init__.py
photobooth/adapters/buttons.py
photobooth/adapters/camera.py
photobooth/adapters/file_store.py
photobooth/adapters/upload.py
photobooth/entrypoints/__init__.py
photobooth/entrypoints/main_widget.py
photobooth/entrypoints/page_widget.py
photobooth/entrypoints/picture_item.py
photobooth/resources/oak.jpg
photobooth/service_layer/__init__.py
photobooth/service_layer/messagebus.py
photobooth-0.0.1.dist-info/METADATA
photobooth-0.0.1.dist-info/WHEEL
photobooth-0.0.1.dist-info/entry_points.txt
photobooth-0.0.1.dist-info/licenses/LICENSE
photobooth-0.0.1.dist-info/RECORD
