Metadata-Version: 2.4
Name: photobooth
Version: 0.0.1
Summary: Photobooth python package. Based on QTs Web Interface and gphoto2 package.
Project-URL: Source Code, https://github.com/pschleiter/photobooth
Author-email: Patrick Schleiter <git.pschleiter@gmail.com>
License-Expression: MIT
License-File: LICENSE
Classifier: Development Status :: 4 - Beta
Classifier: Intended Audience :: End Users/Desktop
Classifier: License :: OSI Approved :: MIT License
Classifier: Programming Language :: Python
Classifier: Programming Language :: Python :: 3.9
Classifier: Programming Language :: Python :: 3.10
Classifier: Programming Language :: Python :: 3.11
Classifier: Programming Language :: Python :: 3.12
Classifier: Topic :: Multimedia :: Graphics :: Capture
Classifier: Topic :: System :: Operating System Kernels :: Linux
Requires-Python: >=3.9
Requires-Dist: click>=8.1.8
Requires-Dist: pyqt5==5.15.2
Provides-Extra: dslr
Requires-Dist: gphoto2>=2.5.1; extra == 'dslr'
Provides-Extra: rpi
Requires-Dist: gpiozero>=2.0.1; extra == 'rpi'
Provides-Extra: upload
Requires-Dist: httpx>=0.28.1; extra == 'upload'
Requires-Dist: pillow>=11.1.0; extra == 'upload'
